{
  "modpublish.publish.title": "Mod veröffentlichen...",
  "modpublish.setToken.title": "ModPublish: Plattform-API-Token festlegen...",
  "release_channel.release": "Release",
  "release_channel.beta": "Beta",
  "release_channel.alpha": "Alpha",
  "dependency.embedded": "Eingebettet",
  "dependency.required": "Erforderlich",
  "dependency.optional": "Optional",
  "dependency.incompatible": "Inkompatibel",
  "dialog.modpublish.publish.environment.title": "Umgebung:",
  "environment.client_and_server": "Client und Server",
  "environment.client_only": "Nur Client",
  "environment.client_only_server_optional": "Nur Client, Server Optional",
  "environment.singleplayer_only": "Nur Einzelspieler",
  "environment.server_only": "Nur Server",
  "environment.server_only_client_optional": "Nur Server, Client Optional",
  "environment.dedicated_server_only": "Nur Dedizierter Server",
  "environment.client_or_server": "Client oder Server",
  "environment.client_or_server_prefers_both": "Client oder Server, Beides Bevorzugt"
}